setuptools_requirements_vcs_version/__init__.py
setuptools_requirements_vcs_version/get_version.py
setuptools_requirements_vcs_version-0.1.0.dist-info/DESCRIPTION.rst
setuptools_requirements_vcs_version-0.1.0.dist-info/METADATA
setuptools_requirements_vcs_version-0.1.0.dist-info/RECORD
setuptools_requirements_vcs_version-0.1.0.dist-info/WHEEL
setuptools_requirements_vcs_version-0.1.0.dist-info/metadata.json
setuptools_requirements_vcs_version-0.1.0.dist-info/top_level.txt
