Metadata-Version: 2.0
Name: setuptools-requirements-vcs-version
Version: 0.1.0
Summary: Extract package version from requirements.txt VCS URLs
Home-page: https://github.com/danielbrownridge/setuptools-requirements-vcs-version
Author: Daniel Brownridge
Author-email: daniel@freshnewpage.com
License: MIT
Platform: UNKNOWN
Classifier: Development Status :: 4 - Beta
Classifier: Intended Audience :: Developers
Classifier: License :: OSI Approved :: MIT License
Classifier: Operating System :: OS Independent
Classifier: Programming Language :: Python :: 3
Classifier: Topic :: Software Development :: Libraries :: Python Modules
Classifier: Topic :: Software Development :: Version Control :: Git
Requires-Dist: requirements-parser
Requires-Dist: semantic-version
